sharemydir.py
sharemydir-1.0.3.dist-info/licenses/LICENSE
sharemydir-1.0.3.dist-info/METADATA
sharemydir-1.0.3.dist-info/WHEEL
sharemydir-1.0.3.dist-info/entry_points.txt
sharemydir-1.0.3.dist-info/top_level.txt
sharemydir-1.0.3.dist-info/RECORD
